LICENSE
README.md
setup.py
askcmd/__init__.py
askcmd/__main__.py
askcmd.egg-info/PKG-INFO
askcmd.egg-info/SOURCES.txt
askcmd.egg-info/dependency_links.txt
askcmd.egg-info/entry_points.txt
askcmd.egg-info/requires.txt
askcmd.egg-info/top_level.txt