Metadata-Version: 2.1
Name: askcmd
Version: 0.1.4
Summary: A command line tool to generate any commands from natural language
Author: lhan
Author-email: lhan12345@hotmail.com
License-File: LICENSE
